{
    "type": "minecraft:crafting_shapeless",
    "ingredients": [
        {
            "item": "nnow:coin_4"
        },
        {
            "item": "nnow:coin_4"
        },
        {
            "item": "nnow:coin_4"
        },
        {
            "item": "nnow:coin_4"
        },
        {
            "item": "nnow:coin_4"
        },
        {
            "item": "nnow:coin_4"
        },
        {
            "item": "nnow:coin_4"
        },
        {
            "item": "nnow:coin_4"
        }
    ],
    "result": {
        "item": "nnow:coin_9",
        "count": 1
    }
}